MANIFEST.in
README.md
pwenc.py
requirements.txt
setup.py
pwenc.egg-info/PKG-INFO
pwenc.egg-info/SOURCES.txt
pwenc.egg-info/dependency_links.txt
pwenc.egg-info/entry_points.txt
pwenc.egg-info/requires.txt
pwenc.egg-info/top_level.txt